{
    "classes_available": [
        "GEN",
        "PWD"
    ],
    "link": "https://traintable.s3.eu-north-1.amazonaws.com/train_pdf2/train_schedule_13422.pdf",
    "operating_days": {
        "friday": false,
        "monday": true,
        "saturday": false,
        "sunday": false,
        "thursday": true,
        "tuesday": false,
        "wednesday": false
    },
    "route_id": "13422-MLDT-NDAE",
    "schedule": [
        {
            "arrival_time": null,
            "day_of_journey": 1,
            "departure_time": "17:00",
            "distance_km": 0.0,
            "sequence_number": 1,
            "station_code": "MLDT",
            "station_name": "MALDA TOWN"
        },
        {
            "arrival_time": "17:27",
            "day_of_journey": 1,
            "departure_time": "17:29",
            "distance_km": 35.0,
            "sequence_number": 2,
            "station_code": "NFK",
            "station_name": "NEW FARAKKA JN"
        },
        {
            "arrival_time": "17:48",
            "day_of_journey": 1,
            "departure_time": "17:50",
            "distance_km": 52.0,
            "sequence_number": 3,
            "station_code": "DGLE",
            "station_name": "DHULIAN GANGA"
        },
        {
            "arrival_time": "18:00",
            "day_of_journey": 1,
            "departure_time": "18:02",
            "distance_km": 62.0,
            "sequence_number": 4,
            "station_code": "NILE",
            "station_name": "NIMITITA"
        },
        {
            "arrival_time": "18:19",
            "day_of_journey": 1,
            "departure_time": "18:21",
            "distance_km": 82.0,
            "sequence_number": 5,
            "station_code": "JRLE",
            "station_name": "JANGIPUR ROAD"
        },
        {
            "arrival_time": "19:05",
            "day_of_journey": 1,
            "departure_time": "19:07",
            "distance_km": 117.0,
            "sequence_number": 6,
            "station_code": "AZ",
            "station_name": "AZIMGANJ JN"
        },
        {
            "arrival_time": "19:20",
            "day_of_journey": 1,
            "departure_time": "19:21",
            "distance_km": 132.0,
            "sequence_number": 7,
            "station_code": "KGLE",
            "station_name": "KHAGRAGHAT ROAD"
        },
        {
            "arrival_time": "19:40",
            "day_of_journey": 1,
            "departure_time": "19:41",
            "distance_km": 159.0,
            "sequence_number": 8,
            "station_code": "BZLE",
            "station_name": "BAZARSAU"
        },
        {
            "arrival_time": "19:59",
            "day_of_journey": 1,
            "departure_time": "20:00",
            "distance_km": 173.0,
            "sequence_number": 9,
            "station_code": "SALE",
            "station_name": "SALAR"
        },
        {
            "arrival_time": "20:15",
            "day_of_journey": 1,
            "departure_time": "20:17",
            "distance_km": 190.0,
            "sequence_number": 10,
            "station_code": "KWAE",
            "station_name": "KATWA"
        },
        {
            "arrival_time": "21:15",
            "day_of_journey": 1,
            "departure_time": null,
            "distance_km": 229.0,
            "sequence_number": 11,
            "station_code": "NDAE",
            "station_name": "NABADWIP DHAM"
        }
    ],
    "train_name": "MLDT NDAE EXP",
    "train_number": "13422",
    "type": "MAIL EXPRESS"
}