{
    "classes_available": [
        "2A",
        "3A",
        "SL",
        "GEN",
        "PWD"
    ],
    "link": "https://traintable.s3.eu-north-1.amazonaws.com/train_pdf2/train_schedule_16187.pdf",
    "operating_days": {
        "friday": true,
        "monday": true,
        "saturday": true,
        "sunday": true,
        "thursday": true,
        "tuesday": true,
        "wednesday": true
    },
    "route_id": "16187-KIK-ERS",
    "schedule": [
        {
            "arrival_time": null,
            "day_of_journey": 1,
            "departure_time": "16:30",
            "distance_km": 0.0,
            "sequence_number": 1,
            "station_code": "KIK",
            "station_name": "KARAIKAL"
        },
        {
            "arrival_time": "16:46",
            "day_of_journey": 1,
            "departure_time": "16:48",
            "distance_km": 11.0,
            "sequence_number": 2,
            "station_code": "NCR",
            "station_name": "NAGORE"
        },
        {
            "arrival_time": "17:03",
            "day_of_journey": 1,
            "departure_time": "17:05",
            "distance_km": 18.0,
            "sequence_number": 3,
            "station_code": "NGT",
            "station_name": "NAGAPPATTINAM JN"
        },
        {
            "arrival_time": "17:30",
            "day_of_journey": 1,
            "departure_time": "17:32",
            "distance_km": 41.0,
            "sequence_number": 4,
            "station_code": "TVR",
            "station_name": "THIRUVARUR JN"
        },
        {
            "arrival_time": "17:53",
            "day_of_journey": 1,
            "departure_time": "17:55",
            "distance_km": 66.0,
            "sequence_number": 5,
            "station_code": "NMJ",
            "station_name": "NIDAMANGALAM JN."
        },
        {
            "arrival_time": "18:23",
            "day_of_journey": 1,
            "departure_time": "18:25",
            "distance_km": 96.0,
            "sequence_number": 6,
            "station_code": "TJ",
            "station_name": "THANJAVUR JN."
        },
        {
            "arrival_time": "18:41",
            "day_of_journey": 1,
            "departure_time": "18:42",
            "distance_km": 113.0,
            "sequence_number": 7,
            "station_code": "BAL",
            "station_name": "BUDALUR"
        },
        {
            "arrival_time": "19:40",
            "day_of_journey": 1,
            "departure_time": "19:50",
            "distance_km": 146.0,
            "sequence_number": 8,
            "station_code": "TPJ",
            "station_name": "TIRUCHCHIRAPPALLI JN."
        },
        {
            "arrival_time": "20:00",
            "day_of_journey": 1,
            "departure_time": "20:02",
            "distance_km": 150.0,
            "sequence_number": 9,
            "station_code": "TP",
            "station_name": "TIRUCHCHIRAPPALLI FORT"
        },
        {
            "arrival_time": "20:49",
            "day_of_journey": 1,
            "departure_time": "20:50",
            "distance_km": 183.0,
            "sequence_number": 10,
            "station_code": "KLT",
            "station_name": "KULITALAI"
        },
        {
            "arrival_time": "21:33",
            "day_of_journey": 1,
            "departure_time": "21:35",
            "distance_km": 221.0,
            "sequence_number": 11,
            "station_code": "KRR",
            "station_name": "KARUR JN."
        },
        {
            "arrival_time": "21:54",
            "day_of_journey": 1,
            "departure_time": "21:55",
            "distance_km": 236.0,
            "sequence_number": 12,
            "station_code": "PGR",
            "station_name": "PUGALUR"
        },
        {
            "arrival_time": "22:55",
            "day_of_journey": 1,
            "departure_time": "23:00",
            "distance_km": 287.0,
            "sequence_number": 13,
            "station_code": "ED",
            "station_name": "ERODE JN"
        },
        {
            "arrival_time": "23:32",
            "day_of_journey": 1,
            "departure_time": "23:33",
            "distance_km": 323.0,
            "sequence_number": 14,
            "station_code": "UKL",
            "station_name": "UTTUKULI"
        },
        {
            "arrival_time": "23:43",
            "day_of_journey": 1,
            "departure_time": "23:48",
            "distance_km": 337.0,
            "sequence_number": 15,
            "station_code": "TUP",
            "station_name": "TIRUPPUR"
        },
        {
            "arrival_time": "01:20",
            "day_of_journey": 2,
            "departure_time": "01:25",
            "distance_km": 387.0,
            "sequence_number": 16,
            "station_code": "CBE",
            "station_name": "COIMBATORE JN"
        },
        {
            "arrival_time": "02:57",
            "day_of_journey": 2,
            "departure_time": "03:00",
            "distance_km": 442.0,
            "sequence_number": 17,
            "station_code": "PGT",
            "station_name": "PALAKKAD JN"
        },
        {
            "arrival_time": "03:25",
            "day_of_journey": 2,
            "departure_time": "03:26",
            "distance_km": 473.0,
            "sequence_number": 18,
            "station_code": "OTP",
            "station_name": "OTTAPPALAM"
        },
        {
            "arrival_time": "04:03",
            "day_of_journey": 2,
            "departure_time": "04:04",
            "distance_km": 502.0,
            "sequence_number": 19,
            "station_code": "WKI",
            "station_name": "WADAKANCHERI"
        },
        {
            "arrival_time": "04:23",
            "day_of_journey": 2,
            "departure_time": "04:26",
            "distance_km": 518.0,
            "sequence_number": 20,
            "station_code": "TCR",
            "station_name": "THRISUR"
        },
        {
            "arrival_time": "04:47",
            "day_of_journey": 2,
            "departure_time": "04:48",
            "distance_km": 542.0,
            "sequence_number": 21,
            "station_code": "IJK",
            "station_name": "IRINJALAKUDA"
        },
        {
            "arrival_time": "04:55",
            "day_of_journey": 2,
            "departure_time": "04:56",
            "distance_km": 548.0,
            "sequence_number": 22,
            "station_code": "CKI",
            "station_name": "CHALAKUDI"
        },
        {
            "arrival_time": "05:13",
            "day_of_journey": 2,
            "departure_time": "05:14",
            "distance_km": 564.0,
            "sequence_number": 23,
            "station_code": "AFK",
            "station_name": "ANGAMALI"
        },
        {
            "arrival_time": "05:26",
            "day_of_journey": 2,
            "departure_time": "05:28",
            "distance_km": 573.0,
            "sequence_number": 24,
            "station_code": "AWY",
            "station_name": "ALUVA"
        },
        {
            "arrival_time": "05:44",
            "day_of_journey": 2,
            "departure_time": "05:45",
            "distance_km": 584.0,
            "sequence_number": 25,
            "station_code": "IPL",
            "station_name": "IDAPALLI"
        },
        {
            "arrival_time": "05:58",
            "day_of_journey": 2,
            "departure_time": "06:00",
            "distance_km": 590.0,
            "sequence_number": 26,
            "station_code": "ERN",
            "station_name": "ERNAKULAM TOWN"
        },
        {
            "arrival_time": "06:45",
            "day_of_journey": 2,
            "departure_time": null,
            "distance_km": 592.0,
            "sequence_number": 27,
            "station_code": "ERS",
            "station_name": "ERNAKULAM JN"
        }
    ],
    "train_name": "KIK ERS EXPRESS",
    "train_number": "16187",
    "type": "MAIL EXPRESS"
}